{
  "note": "Working dataset for the app. General actions/reactions available to all characters, plus heroic-path talents (key talent + Investigator/Spy/Thief-style specialties for all 6 paths). 'eff' is terse shorthand in our own words. 'spec' = specialty within the path. act '?' = the source used an icon we couldn't read; treat as the stated count, else 1 action — verify against your book. 'tier' is 1 for all path talents (real gating is in 'pre' and the talent-tree order).",
  "version": "0.3.0",
  "abilities": [
    { "id": "gen-strike", "name": "Strike", "src": "general", "kind": "action", "tier": 0, "act": "1a", "cost": "", "rng": "reach", "vs": "phys", "eff": "unarmed/weapon atk vs Physical. Repeatable, but each uses a different hand; offhand costs 2F." },
    { "id": "gen-move", "name": "Move", "src": "general", "kind": "action", "tier": 0, "act": "1a", "cost": "", "rng": "self", "vs": "", "eff": "move up to movement rate; Slowed conditions reduce it. Repeatable." },
    { "id": "gen-interact", "name": "Interact", "src": "general", "kind": "action", "tier": 0, "act": "1a", "cost": "", "rng": "reach", "vs": "", "eff": "manipulate a nearby object (draw weapon, open door, grab item); no test. Repeatable." },
    { "id": "gen-use-skill", "name": "Use a Skill", "src": "general", "kind": "action", "tier": 0, "act": "1a", "cost": "", "rng": "self", "vs": "", "eff": "roll a skill to handle a battlefield task (hide, search, treat)." },
    { "id": "gen-gain-advantage", "name": "Gain Advantage", "src": "general", "kind": "action", "tier": 0, "act": "1a", "cost": "", "rng": "self", "vs": "varies", "eff": "skill test vs foe defense; success -> advantage on next test vs that foe with a different skill." },
    { "id": "gen-brace", "name": "Brace", "src": "general", "kind": "action", "tier": 0, "act": "1a", "cost": "", "rng": "self", "vs": "", "eff": "take cover within 5ft; attacks vs you get disadvantage until you move/attack." },
    { "id": "gen-disengage", "name": "Disengage", "src": "general", "kind": "action", "tier": 0, "act": "1a", "cost": "", "rng": "self", "vs": "", "eff": "move 5ft without triggering Reactive Strikes." },
    { "id": "gen-grapple", "name": "Grapple", "src": "general", "kind": "action", "tier": 0, "act": "1a", "cost": "", "rng": "reach", "vs": "phys", "eff": "Athletics vs Physical; success -> target Restrained while in reach." },
    { "id": "gen-shove", "name": "Shove", "src": "general", "kind": "action", "tier": 0, "act": "1a", "cost": "", "rng": "reach", "vs": "phys", "eff": "Athletics vs Physical; success -> push/pull 5ft; ends a Grapple on you." },
    { "id": "gen-recover", "name": "Recover", "src": "general", "kind": "action", "tier": 0, "act": "1a+", "cost": "", "rng": "self", "vs": "", "eff": "roll recovery die to regain health/focus (as a short rest). Once per scene; can spend extra actions." },
    { "id": "gen-ready", "name": "Ready", "src": "general", "kind": "action", "tier": 0, "act": "var", "cost": "", "rng": "self", "vs": "", "eff": "pick a trigger + an action; use that action when the trigger fires before your next turn. Costs the action's cost +1a." },
    { "id": "gen-banter", "name": "Banter", "src": "general", "kind": "action", "tier": 0, "act": "free", "cost": "", "rng": "self", "vs": "", "eff": "speak briefly; nuanced/persuasive speech needs Use a Skill instead." },
    { "id": "gen-drop", "name": "Drop", "src": "general", "kind": "action", "tier": 0, "act": "free", "cost": "", "rng": "self", "vs": "", "eff": "drop held objects." },
    { "id": "gen-aid", "name": "Aid", "src": "general", "kind": "reaction", "tier": 0, "act": "rea", "cost": "1F", "rng": "varies", "vs": "", "eff": "trigger: ally about to test -> grant them an advantage." },
    { "id": "gen-dodge", "name": "Dodge", "src": "general", "kind": "reaction", "tier": 0, "act": "rea", "cost": "1F", "rng": "self", "vs": "", "eff": "trigger: an attack is aimed at you -> impose disadvantage on it. Not vs area/multi-target." },
    { "id": "gen-avoid-danger", "name": "Avoid Danger", "src": "general", "kind": "reaction", "tier": 0, "act": "rea", "cost": "", "rng": "self", "vs": "", "eff": "trigger: imperiled by surroundings -> Agility test (DC = triggering result, else 15) to escape/mitigate." },
    { "id": "gen-reactive-strike", "name": "Reactive Strike", "src": "general", "kind": "reaction", "tier": 0, "act": "rea", "cost": "1F", "rng": "reach", "vs": "phys", "eff": "trigger: foe willingly steps out of your reach -> melee/unarmed atk vs Physical. Not vs instantaneous movement." },
    { "id": "agent-opportunist", "name": "Opportunist", "src": "agent", "kind": "talent", "key": true, "tier": 1, "pre": "", "act": "free", "cost": "", "rng": "self", "vs": "", "eff": "1x each round: re-roll one plot-die result." },
    { "id": "envoy-rousing-presence", "name": "Rousing Presence", "src": "envoy", "kind": "talent", "key": true, "tier": 1, "pre": "", "act": "1a?", "cost": "", "rng": "varies", "vs": "", "eff": "make an ally Determined." },
    { "id": "hunter-seek-quarry", "name": "Seek Quarry", "src": "hunter", "kind": "talent", "key": true, "tier": 1, "pre": "", "act": "1a?", "cost": "", "rng": "varies", "vs": "", "eff": "mark a target to pursue; gain an advantage against it." },
    { "id": "leader-decisive-command", "name": "Decisive Command", "src": "leader", "kind": "talent", "key": true, "tier": 1, "pre": "", "act": "1a?", "cost": "", "rng": "varies", "vs": "", "eff": "give an ally a bonus d4 ('command die') applied to one roll." },
    { "id": "scholar-erudition", "name": "Erudition", "src": "scholar", "kind": "talent", "key": true, "tier": 1, "pre": "", "act": "none", "cost": "", "rng": "self", "vs": "", "eff": "gain bonus skill ranks you can reallocate." },
    { "id": "warrior-vigilant-stance", "name": "Vigilant Stance", "src": "warrior", "kind": "talent", "key": true, "tier": 1, "pre": "", "act": "1a?", "cost": "", "rng": "self", "vs": "", "eff": "adopt a defensive stance granting added responsiveness and flexibility." },
    { "id": "agent-watchful-eye", "name": "Watchful Eye", "src": "agent", "kind": "talent", "tier": 1, "spec": "Investigator", "pre": "Deduction 1+", "act": "rea", "cost": "", "rng": "20ft", "vs": "", "eff": "trigger: willing ally within 20ft rolls a plot die -> use Opportunist on their plot die" },
    { "id": "agent-get-em-talking", "name": "Get 'Em Talking", "src": "agent", "kind": "talent", "tier": 1, "spec": "Investigator", "pre": "Insight 2+", "act": "1a?", "cost": "1F", "rng": "varies", "vs": "spir", "eff": "1F: Deduction vs spir of an influenceable foe; success -> learn their motivation; raise stakes on tests leveraging it this scene" },
    { "id": "agent-quick-analysis", "name": "Quick Analysis", "src": "agent", "kind": "talent", "tier": 1, "spec": "Investigator", "pre": "", "act": "free?", "cost": "2F", "rng": "self", "vs": "", "eff": "2F -> gain an advantage, usable only on cognitive tests via Use a Skill / Gain Advantage / an Agent talent" },
    { "id": "agent-baleful", "name": "Baleful", "src": "agent", "kind": "talent", "tier": 1, "spec": "Investigator", "pre": "", "act": "none", "cost": "", "rng": "self", "vs": "", "eff": "passive: foes must spend extra focus = your tier to resist your influence" },
    { "id": "agent-gather-evidence", "name": "Gather Evidence", "src": "agent", "kind": "talent", "tier": 1, "spec": "Investigator", "pre": "Insight 2+", "act": "none", "cost": "", "rng": "self", "vs": "", "eff": "passive: succeed on a cognitive test vs a character -> become Focused EONT; gain Legal Codes expertise" },
    { "id": "agent-hardy", "name": "Hardy", "src": "agent", "kind": "talent", "tier": 1, "spec": "Investigator", "pre": "", "act": "none", "cost": "", "rng": "self", "vs": "", "eff": "passive: +1 max health per level (retroactive)" },
    { "id": "agent-sleuths-instincts", "name": "Sleuth's Instincts", "src": "agent", "kind": "talent", "tier": 1, "spec": "Investigator", "pre": "Deduction 3+", "act": "none", "cost": "", "rng": "self", "vs": "", "eff": "passive: adv on cognitive tests vs foes whose motivation you know; you auto-know when they lie to you" },
    { "id": "agent-close-the-case", "name": "Close the Case", "src": "agent", "kind": "talent", "tier": 1, "spec": "Investigator", "pre": "Deduction 3+", "act": "1a?", "cost": "3F", "rng": "varies", "vs": "cog", "eff": "1/scene, 3F: Deduction vs cog of an influenceable foe (adv if you know their motive); success -> they back down; fail -> they get adv vs you EONT" },
    { "id": "agent-sure-outcome", "name": "Sure Outcome", "src": "agent", "kind": "talent", "tier": 1, "spec": "Spy", "pre": "Insight 2+", "act": "free?", "cost": "2F", "rng": "self", "vs": "", "eff": "when you use Opportunist, 2F to flip the plot die to a chosen result instead of rerolling" },
    { "id": "agent-plausible-excuse", "name": "Plausible Excuse", "src": "agent", "kind": "talent", "tier": 1, "spec": "Spy", "pre": "Deception 1+", "act": "rea", "cost": "2F", "rng": "varies", "vs": "", "eff": "trigger: discovered while hiding/skulking -> 2F to feign innocence; all who sense you believe it; resisting costs them extra F = Deception ranks; gain Sleight of Hand expertise" },
    { "id": "agent-collected", "name": "Collected", "src": "agent", "kind": "talent", "tier": 1, "spec": "Spy", "pre": "", "act": "none", "cost": "", "rng": "self", "vs": "", "eff": "passive: +2 cog defense, +2 spir defense" },
    { "id": "agent-cover-story", "name": "Cover Story", "src": "agent", "kind": "talent", "tier": 1, "spec": "Spy", "pre": "", "act": "none", "cost": "", "rng": "self", "vs": "", "eff": "gain a false identity + a relevant cultural expertise" },
    { "id": "agent-subtle-takedown", "name": "Subtle Takedown", "src": "agent", "kind": "talent", "tier": 1, "spec": "Spy", "pre": "Insight 3+", "act": "1a?", "cost": "", "rng": "reach", "vs": "cog", "eff": "unarmed atk w/ Insight vs cog of a Surprised/unaware foe your size or smaller, raise stakes; hit -> can't communicate EONT; Opportunity -> auto-Grapple + Prone" },
    { "id": "agent-mighty", "name": "Mighty", "src": "agent", "kind": "talent", "tier": 1, "spec": "Spy", "pre": "", "act": "none", "cost": "", "rng": "self", "vs": "", "eff": "passive: on weapon/unarmed hit, per action-die spent on that atk -> +(1 + tier) damage" },
    { "id": "agent-mercurial-facade", "name": "Mercurial Facade", "src": "agent", "kind": "talent", "tier": 1, "spec": "Spy", "pre": "Deception 3+", "act": "none", "cost": "", "rng": "self", "vs": "", "eff": "disguise yourself via Deception, no supplies needed; first to see through it is Surprised EONT" },
    { "id": "agent-high-society-contacts", "name": "High Society Contacts", "src": "agent", "kind": "talent", "tier": 1, "spec": "Spy", "pre": "Patron in high society", "act": "free?", "cost": "2F", "rng": "self", "vs": "", "eff": "gain High Society expertise; 2F on a high-society social test -> add an Opportunity to result" },
    { "id": "agent-risky-behavior", "name": "Risky Behavior", "src": "agent", "kind": "talent", "tier": 1, "spec": "Thief", "pre": "Insight 2+", "act": "free", "cost": "1F", "rng": "self", "vs": "", "eff": "before a test, 1F to raise the stakes" },
    { "id": "agent-double-down", "name": "Double Down", "src": "agent", "kind": "talent", "tier": 1, "spec": "Thief", "pre": "", "act": "free?", "cost": "", "rng": "self", "vs": "", "eff": "after Opportunist, reroll the die once more (must keep it); a bad result costs 2 focus" },
    { "id": "agent-cheap-shot", "name": "Cheap Shot", "src": "agent", "kind": "talent", "tier": 1, "spec": "Thief", "pre": "", "act": "1a?", "cost": "1F", "rng": "reach", "vs": "cog", "eff": "hand free + 1F: unarmed atk w/ Thievery vs cog of a foe your size or smaller, raise stakes; hit -> Stunned EONT; Opportunity -> steal a stowed item" },
    { "id": "agent-surefooted", "name": "Surefooted", "src": "agent", "kind": "talent", "tier": 1, "spec": "Thief", "pre": "", "act": "none", "cost": "", "rng": "self", "vs": "", "eff": "passive: +10ft movement; reduce falling/dangerous-terrain damage by 2x tier" },
    { "id": "agent-underworld-contacts", "name": "Underworld Contacts", "src": "agent", "kind": "talent", "tier": 1, "spec": "Thief", "pre": "Patron/follower in criminal underworld", "act": "free?", "cost": "2F", "rng": "self", "vs": "", "eff": "gain Criminal Groups expertise; 2F on a social test vs criminals -> add an Opportunity to result" },
    { "id": "agent-shadow-step", "name": "Shadow Step", "src": "agent", "kind": "talent", "tier": 1, "spec": "Thief", "pre": "Thievery 3+", "act": "free?", "cost": "2F", "rng": "self", "vs": "cog", "eff": "after Disengage, 2F: Thievery vs each sensing enemy's cog (adv in cover/obscured); beat one -> hidden from them as if you'd hidden via Stealth" },
    { "id": "agent-fast-talker", "name": "Fast Talker", "src": "agent", "kind": "talent", "tier": 1, "spec": "Thief", "pre": "Insight 3+", "act": "free?", "cost": "2F", "rng": "self", "vs": "", "eff": "2F -> gain an advantage, usable only on spiritual tests via Use a Skill / Gain Advantage / an Agent talent" },
    { "id": "agent-tricksters-hand", "name": "Trickster's Hand", "src": "agent", "kind": "talent", "tier": 1, "spec": "Thief", "pre": "Thievery 3+", "act": "free?", "cost": "2F", "rng": "self", "vs": "", "eff": "2F -> gain an advantage, usable only on physical tests via Use a Skill / Gain Advantage / an Agent talent" },
    { "id": "envoy-steadfast-challenge", "name": "Steadfast Challenge", "src": "envoy", "kind": "talent", "tier": 1, "spec": "Diplomat", "pre": "Discipline 1+", "act": "1a?", "cost": "1F", "rng": "varies", "vs": "spir", "eff": "1F: Discipline test vs spir of an influenceable foe; hit -> Disoriented + disadv on their tests vs you EONT" },
    { "id": "envoy-collected", "name": "Collected", "src": "envoy", "kind": "talent", "tier": 1, "spec": "Diplomat", "pre": "", "act": "none", "cost": "", "rng": "self", "vs": "", "eff": "passive: +2 cog defense, +2 spir defense" },
    { "id": "envoy-withering-retort", "name": "Withering Retort", "src": "envoy", "kind": "talent", "tier": 1, "spec": "Diplomat", "pre": "Discipline 2+", "act": "rea", "cost": "1F", "rng": "varies", "vs": "spir", "eff": "trigger: sensed foe atks you -> fire Steadfast Challenge as reaction; also +deflect vs that atk = Discipline ranks" },
    { "id": "envoy-well-dressed", "name": "Well Dressed", "src": "envoy", "kind": "talent", "tier": 1, "spec": "Diplomat", "pre": "", "act": "none", "cost": "", "rng": "self", "vs": "", "eff": "gain Fashion expertise; in Presentable armor/fancy clothes -> adv on first Deception/Leadership/Persuasion test each scene" },
    { "id": "envoy-calm-appeal", "name": "Calm Appeal", "src": "envoy", "kind": "talent", "tier": 1, "spec": "Diplomat", "pre": "Discipline 2+", "act": "free?", "cost": "1F", "rng": "varies", "vs": "", "eff": "when Steadfast Challenge Disorients a foe, 1F -> pacify them rest of scene (broken if attacked or ally hurt); resisting costs them extra F = Discipline ranks" },
    { "id": "envoy-high-society-contacts", "name": "High Society Contacts", "src": "envoy", "kind": "talent", "tier": 1, "spec": "Diplomat", "pre": "Patron in high society", "act": "free?", "cost": "2F", "rng": "self", "vs": "", "eff": "gain High Society expertise; 2F on a high-society social test -> add an Opportunity to result" },
    { "id": "envoy-peaceful-solution", "name": "Peaceful Solution", "src": "envoy", "kind": "talent", "tier": 1, "spec": "Diplomat", "pre": "Discipline 3+", "act": "free?", "cost": "", "rng": "self", "vs": "", "eff": "if all non-minion foes pacified & others agree to stop -> end combat, becomes conversation; GM may allow non-combat use" },
    { "id": "envoy-practiced-oratory", "name": "Practiced Oratory", "src": "envoy", "kind": "talent", "tier": 1, "spec": "Diplomat", "pre": "Persuasion 3+", "act": "free?", "cost": "var", "rng": "self", "vs": "", "eff": "when you use Rousing Presence/Steadfast Challenge, pay up to Persuasion ranks in F -> that many extra targets" },
    { "id": "envoy-customary-garb", "name": "Customary Garb", "src": "envoy", "kind": "talent", "tier": 1, "spec": "Faithful", "pre": "", "act": "none", "cost": "", "rng": "self", "vs": "", "eff": "passive: while in Presentable armor/station-appropriate clothes, +2 phys defense, +2 spir defense" },
    { "id": "envoy-galvanize", "name": "Galvanize", "src": "envoy", "kind": "talent", "tier": 1, "spec": "Faithful", "pre": "", "act": "1a?", "cost": "", "rng": "varies", "vs": "", "eff": "1/scene: influenceable ally rolls recovery die, recovers that much F (no action for them)" },
    { "id": "envoy-devoted-presence", "name": "Devoted Presence", "src": "envoy", "kind": "talent", "tier": 1, "spec": "Faithful", "pre": "Lore 1+", "act": "free?", "cost": "1F", "rng": "varies", "vs": "", "eff": "on Rousing Presence, 1F per target -> clear any of: Prone, Slowed, Stunned, Surprised from them" },
    { "id": "envoy-composed", "name": "Composed", "src": "envoy", "kind": "talent", "tier": 1, "spec": "Faithful", "pre": "", "act": "none", "cost": "", "rng": "self", "vs": "", "eff": "passive: max & current F increase by tier; scales as tier rises" },
    { "id": "envoy-stalwart-presence", "name": "Stalwart Presence", "src": "envoy", "kind": "talent", "tier": 1, "spec": "Faithful", "pre": "Discipline 2+", "act": "free?", "cost": "1F", "rng": "varies", "vs": "", "eff": "on Rousing Presence, 1F -> +2 to one chosen defense of target until end of next round" },
    { "id": "envoy-applied-motivation", "name": "Applied Motivation", "src": "envoy", "kind": "talent", "tier": 1, "spec": "Faithful", "pre": "Discipline 2+", "act": "none", "cost": "", "rng": "self", "vs": "", "eff": "passive: when you make a character recover F, they get bonus F = half Lore ranks (round up)" },
    { "id": "envoy-sage-counsel", "name": "Sage Counsel", "src": "envoy", "kind": "talent", "tier": 1, "spec": "Faithful", "pre": "Lore 3+", "act": "free?", "cost": "1F", "rng": "varies", "vs": "", "eff": "after Aiding an ally, 1F -> also give them the Rousing Presence benefit (no action)" },
    { "id": "envoy-inspired-zeal", "name": "Inspired Zeal", "src": "envoy", "kind": "talent", "tier": 1, "spec": "Faithful", "pre": "Discipline 3+", "act": "free?", "cost": "", "rng": "varies", "vs": "", "eff": "after a sensed ally spends Determined for an Opportunity, pick up to Discipline-ranks influenceable allies -> each recovers 1F" },
    { "id": "envoy-sound-advice", "name": "Sound Advice", "src": "envoy", "kind": "talent", "tier": 1, "spec": "Mentor", "pre": "", "act": "free?", "cost": "1F", "rng": "varies", "vs": "", "eff": "after an influenceable ally fails a skill test, 1F -> use Rousing Presence on them as a reaction" },
    { "id": "envoy-practical-demonstration", "name": "Practical Demonstration", "src": "envoy", "kind": "talent", "tier": 1, "spec": "Mentor", "pre": "Leadership 1+", "act": "free?", "cost": "", "rng": "self", "vs": "", "eff": "after you succeed on an atk or Gain Advantage test -> use Rousing Presence as a free reaction" },
    { "id": "envoy-lessons-in-patience", "name": "Lessons in Patience", "src": "envoy", "kind": "talent", "tier": 1, "spec": "Mentor", "pre": "Discipline 2+", "act": "none", "cost": "", "rng": "self", "vs": "", "eff": "gain Motivational Speech expertise; after using Rousing Presence, target recovers 1F" },
    { "id": "envoy-mighty", "name": "Mighty", "src": "envoy", "kind": "talent", "tier": 1, "spec": "Mentor", "pre": "", "act": "none", "cost": "", "rng": "self", "vs": "", "eff": "passive: on weapon/unarmed hit, per action-die spent on that atk -> +(1 + tier) damage" },
    { "id": "envoy-instill-confidence", "name": "Instill Confidence", "src": "envoy", "kind": "talent", "tier": 1, "spec": "Mentor", "pre": "A companion", "act": "none", "cost": "", "rng": "varies", "vs": "", "eff": "Rousing Presence may instead make target Focused (not Determined) until scene ends" },
    { "id": "envoy-guiding-oration", "name": "Guiding Oration", "src": "envoy", "kind": "talent", "tier": 1, "spec": "Mentor", "pre": "Leadership 2+", "act": "free?", "cost": "", "rng": "10ft", "vs": "", "eff": "after you succeed at Gain Advantage, pick an influenceable ally within 10ft of your target -> they get adv on next test vs that target EONT" },
    { "id": "envoy-foresight", "name": "Foresight", "src": "envoy", "kind": "talent", "tier": 1, "spec": "Mentor", "pre": "Discipline 3+", "act": "none", "cost": "", "rng": "self", "vs": "", "eff": "passive: gain one extra action-die at combat start and again each turn after" },
    { "id": "envoy-rallying-shout", "name": "Rallying Shout", "src": "envoy", "kind": "talent", "tier": 1, "spec": "Mentor", "pre": "Leadership 3+", "act": "free?", "cost": "", "rng": "varies", "vs": "", "eff": "Rousing Presence may target a sensed Unconscious ally -> ends Unconscious; if at 0 health they roll recovery die + Leadership ranks as restored health" },
    { "id": "hunter-tagging-shot", "name": "Tagging Shot", "src": "hunter", "kind": "talent", "tier": 1, "spec": "Archer", "pre": "Perception 2+", "act": "1a?", "cost": "", "rng": "self", "vs": "phys", "eff": "step 5ft + ranged atk vs phys; hit or graze -> target becomes your Seek Quarry quarry" },
    { "id": "hunter-combat-training", "name": "Combat Training", "src": "hunter", "kind": "talent", "tier": 1, "spec": "Archer", "pre": "", "act": "none", "cost": "", "rng": "self", "vs": "", "eff": "gain weapon+armor+Military Life expertises; 1/round on a miss, graze a target w/o spending F" },
    { "id": "hunter-sharp-eye", "name": "Sharp Eye", "src": "hunter", "kind": "talent", "tier": 1, "spec": "Archer", "pre": "", "act": "1a?", "cost": "", "rng": "self", "vs": "cog", "eff": "observe quarry (or any char 1min) + Perception vs cog; success -> learn one: weakest attribute, weakest defense, or whether hp/F/I is over half spent" },
    { "id": "hunter-steady-aim", "name": "Steady Aim", "src": "hunter", "kind": "talent", "tier": 1, "spec": "Archer", "pre": "Agility 1+", "act": "1a?", "cost": "", "rng": "self", "vs": "", "eff": "EONT: ranged weapon short+long ranges +50%; ranged hits deal bonus dmg = Perception ranks" },
    { "id": "hunter-exploit-weakness", "name": "Exploit Weakness", "src": "hunter", "kind": "talent", "tier": 1, "spec": "Archer", "pre": "Perception 3+", "act": "free?", "cost": "", "rng": "self", "vs": "", "eff": "use Gain Advantage as a faster action, only vs your quarry" },
    { "id": "hunter-backstep", "name": "Backstep", "src": "hunter", "kind": "talent", "tier": 1, "spec": "Archer", "pre": "Agility 2+", "act": "free?", "cost": "2F", "rng": "self", "vs": "", "eff": "after a ranged atk, 2F: Disengage as a free action; if your turn ends in cover/obscured -> gain Brace" },
    { "id": "hunter-unrelenting-salvo", "name": "Unrelenting Salvo", "src": "hunter", "kind": "talent", "tier": 1, "spec": "Archer", "pre": "Agility 3+", "act": "none", "cost": "", "rng": "self", "vs": "", "eff": "your ranged weapon may Strike the same quarry repeatedly in a turn (ignores the 1-Strike-per-hand limit)" },
    { "id": "hunter-hardy", "name": "Hardy", "src": "hunter", "kind": "talent", "tier": 1, "spec": "Archer", "pre": "", "act": "none", "cost": "", "rng": "self", "vs": "", "eff": "passive: +1 max hp per level, applied retroactively to all levels" },
    { "id": "hunter-startling-blow", "name": "Startling Blow", "src": "hunter", "kind": "talent", "tier": 1, "spec": "Assassin", "pre": "Stealth 1+", "act": "1a?", "cost": "", "rng": "melee", "vs": "cog", "eff": "unarmed/improvised atk vs cog of foe your size or smaller; hit or graze -> Surprised EONT" },
    { "id": "hunter-killing-edge", "name": "Killing Edge", "src": "hunter", "kind": "talent", "tier": 1, "spec": "Assassin", "pre": "Perception 2+", "act": "none", "cost": "", "rng": "self", "vs": "", "eff": "gain Knives+Slings expertises; while wielding a knife/sling it gains the Deadly + Quickdraw expert traits" },
    { "id": "hunter-fatal-thrust", "name": "Fatal Thrust", "src": "hunter", "kind": "talent", "tier": 1, "spec": "Assassin", "pre": "Perception 3+", "act": "1a?", "cost": "", "rng": "melee", "vs": "cog", "eff": "light weapon melee atk vs cog of a Surprised/unaware/non-threatened foe; +4d4 dmg (6d4 t3, 8d4 t4, 10d4 t5); Discreet -> 2 adv; each max-value dmg die -> target -2 injury roll" },
    { "id": "hunter-shadowing", "name": "Shadowing", "src": "hunter", "kind": "talent", "tier": 1, "spec": "Assassin", "pre": "Stealth 2+", "act": "none", "cost": "", "rng": "self", "vs": "spir", "eff": "adv to avoid quarry's senses, quarry has disadv to sense you; succeeding vs spir while in cover/obscured + 3F -> make that target your quarry" },
    { "id": "hunter-mighty", "name": "Mighty", "src": "hunter", "kind": "talent", "tier": 1, "spec": "Assassin", "pre": "", "act": "none", "cost": "", "rng": "self", "vs": "", "eff": "passive: on weapon/unarmed hit, per action spent on the atk deal +1+tier dmg" },
    { "id": "hunter-swift-strikes", "name": "Swift Strikes", "src": "hunter", "kind": "talent", "tier": 1, "spec": "Assassin", "pre": "", "act": "free?", "cost": "1F", "rng": "self", "vs": "", "eff": "1F: a second Strike with a hand already used to Strike this turn" },
    { "id": "hunter-cold-eyes", "name": "Cold Eyes", "src": "hunter", "kind": "talent", "tier": 1, "spec": "Assassin", "pre": "", "act": "none", "cost": "", "rng": "self", "vs": "", "eff": "after killing/incapacitating your quarry: recover 1F + name a new sensed enemy as quarry" },
    { "id": "hunter-sidestep", "name": "Sidestep", "src": "hunter", "kind": "talent", "tier": 1, "spec": "Assassin", "pre": "Stealth 3+", "act": "none", "cost": "", "rng": "self", "vs": "", "eff": "gain an extra action at combat start + each turn, usable only to Dodge; disabled while wearing armor w/ deflect 2+" },
    { "id": "hunter-deadly-trap", "name": "Deadly Trap", "src": "hunter", "kind": "talent", "tier": 1, "spec": "Tracker", "pre": "Survival 1+", "act": "var", "cost": "", "rng": "reach", "vs": "", "eff": "conceal a 5ft trap (max = Survival ranks), triggers on touch, adv vs quarry, can't graze. Entangling: Survival vs cog, 2d4 impact + Immobilized 1rd + difficult terrain. Impaling: vs phys, 2d4 keen + Afflicted[3+Survival] 1rd, spend action -> injury" },
    { "id": "hunter-experienced-trapper", "name": "Experienced Trapper", "src": "hunter", "kind": "talent", "tier": 1, "spec": "Tracker", "pre": "Perception 2+", "act": "none", "cost": "", "rng": "self", "vs": "", "eff": "forage w/o focus on a short rest, auto-succeed foraging food/water (feeds = Survival ranks); craft tools via Survival; Deadly Trap dmg -> 2d6, condition duration -> 2rd" },
    { "id": "hunter-animal-bond", "name": "Animal Bond", "src": "hunter", "kind": "talent", "tier": 1, "spec": "Tracker", "pre": "Animal companion", "act": "none", "cost": "", "rng": "10ft", "vs": "", "eff": "upgrade companion; while sensed within 10ft, +1 all defenses & it moves w/ you; spend action -> companion acts now (extra actions, fewer next turn). Track action -> sensed target becomes quarry" },
    { "id": "hunter-protective-bond", "name": "Protective Bond", "src": "hunter", "kind": "talent", "tier": 1, "spec": "Tracker", "pre": "", "act": "1a?", "cost": "", "rng": "30ft", "vs": "", "eff": "send companion to guard an ally within 30ft; while it stays in the ally's reach, ally gets your Animal Bond defense bonus instead of you; ends if recalled or scene ends" },
    { "id": "hunter-feral-connection", "name": "Feral Connection", "src": "hunter", "kind": "talent", "tier": 1, "spec": "Tracker", "pre": "Survival 2+", "act": "none", "cost": "", "rng": "self", "vs": "", "eff": "companion +5*tier max hp, +2 all defenses, +Survival ranks to its tests; gain Animal Care expertise" },
    { "id": "hunter-surefooted", "name": "Surefooted", "src": "hunter", "kind": "talent", "tier": 1, "spec": "Tracker", "pre": "", "act": "none", "cost": "", "rng": "self", "vs": "", "eff": "passive: +10 movement; reduce falling/dangerous-terrain dmg by 2*tier" },
    { "id": "hunter-hunters-edge", "name": "Hunter's Edge", "src": "hunter", "kind": "talent", "tier": 1, "spec": "Tracker", "pre": "Survival 3+", "act": "none", "cost": "", "rng": "self", "vs": "", "eff": "companion gains adv vs your quarry; Deadly Trap dmg -> 2d8, condition duration -> 3rd" },
    { "id": "hunter-pack-hunting", "name": "Pack Hunting", "src": "hunter", "kind": "talent", "tier": 1, "spec": "Tracker", "pre": "Perception 3+", "act": "rea", "cost": "1F", "rng": "self", "vs": "", "eff": "trigger: an ally with line of effect strikes your quarry -> 1F: add Survival ranks to their atk test or damage roll" },
    { "id": "leader-combat-coordination", "name": "Combat Coordination", "src": "leader", "kind": "talent", "tier": 1, "spec": "Champion", "pre": "Leadership 2+", "act": "free", "cost": "", "rng": "20ft", "vs": "", "eff": "after a Strike -> trigger Decisive Command for free (no action); if the Strike missed, also skip its F cost" },
    { "id": "leader-valiant-intervention", "name": "Valiant Intervention", "src": "leader", "kind": "talent", "tier": 1, "spec": "Champion", "pre": "Athletics 1+", "act": "1a?", "cost": "1F", "rng": "self", "vs": "spir", "eff": "1F: shift up to 10ft, then Athletics vs spir of an influenceable foe; success -> disadv on their tests vs your allies EONT; if they resist, you get adv vs them EONT" },
    { "id": "leader-imposing-posture", "name": "Imposing Posture", "src": "leader", "kind": "talent", "tier": 1, "spec": "Champion", "pre": "Athletics 2+", "act": "none", "cost": "", "rng": "reach", "vs": "", "eff": "when a foe within weapon reach resists your influence -> they become Disoriented EONT" },
    { "id": "leader-hardy", "name": "Hardy", "src": "leader", "kind": "talent", "tier": 1, "spec": "Champion", "pre": "", "act": "none", "cost": "", "rng": "self", "vs": "", "eff": "passive: max & current HP +1 per level, applied retroactively to all levels" },
    { "id": "leader-mighty", "name": "Mighty", "src": "leader", "kind": "talent", "tier": 1, "spec": "Champion", "pre": "", "act": "none", "cost": "", "rng": "self", "vs": "", "eff": "passive: on weapon/unarmed hit, per action-point spent on that atk -> +1+tier dmg" },
    { "id": "leader-resilient-hero", "name": "Resilient Hero", "src": "leader", "kind": "talent", "tier": 1, "spec": "Champion", "pre": "Athletics 3+", "act": "rea", "cost": "", "rng": "self", "vs": "", "eff": "1/scene: just before dropping to 0 HP -> set HP to your Athletics mod instead" },
    { "id": "leader-resolute-stand", "name": "Resolute Stand", "src": "leader", "kind": "talent", "tier": 1, "spec": "Champion", "pre": "Athletics 1+", "act": "none", "cost": "var", "rng": "self", "vs": "", "eff": "Valiant Intervention: spend F up to Leadership ranks -> add that many extra targets; affected targets can't make Reactive Strikes vs your allies EONT" },
    { "id": "leader-demonstrative-command", "name": "Demonstrative Command", "src": "leader", "kind": "talent", "tier": 1, "spec": "Champion", "pre": "Leadership 2+", "act": "free", "cost": "1F", "rng": "self", "vs": "", "eff": "command die +1 size on gain; before an Athletics/Agility/Leadership test, 1F -> roll command die & add to your d20" },
    { "id": "leader-composed", "name": "Composed", "src": "leader", "kind": "talent", "tier": 1, "spec": "Officer", "pre": "", "act": "none", "cost": "", "rng": "self", "vs": "", "eff": "passive: max & current F +tier; rises with tier" },
    { "id": "leader-through-the-fray", "name": "Through the Fray", "src": "leader", "kind": "talent", "tier": 1, "spec": "Officer", "pre": "Persuasion 1+", "act": "1a?", "cost": "", "rng": "20ft", "vs": "", "eff": "pick an influenceable ally within 20ft -> before your turn ends they may Disengage or Gain Advantage as a free action" },
    { "id": "leader-well-supplied", "name": "Well Supplied", "src": "leader", "kind": "talent", "tier": 1, "spec": "Officer", "pre": "Persuasion 2+", "act": "none", "cost": "2F", "rng": "self", "vs": "", "eff": "gain Military Logistics expertise; on a requisition/allocate-resources test, 2F -> add an Opportunity" },
    { "id": "leader-customary-garb", "name": "Customary Garb", "src": "leader", "kind": "talent", "tier": 1, "spec": "Officer", "pre": "", "act": "none", "cost": "", "rng": "self", "vs": "", "eff": "passive: while visibly wearing Presentable armor/appropriate clothing, phys & spir defenses +2" },
    { "id": "leader-relentless-march", "name": "Relentless March", "src": "leader", "kind": "talent", "tier": 1, "spec": "Officer", "pre": "Persuasion 3+", "act": "none", "cost": "", "rng": "varies", "vs": "", "eff": "after Decisive Command on an ally: EONT their speed +10ft & they ignore Exhausted, Slowed, Surprised" },
    { "id": "leader-confident-command", "name": "Confident Command", "src": "leader", "kind": "talent", "tier": 1, "spec": "Officer", "pre": "Leadership 2+", "act": "free", "cost": "1F", "rng": "self", "vs": "", "eff": "command die +1 size on gain; before an Intimidation/Leadership/Persuasion test, 1F -> roll command die & add to your d20" },
    { "id": "leader-synchronized-assault", "name": "Synchronized Assault", "src": "leader", "kind": "talent", "tier": 1, "spec": "Officer", "pre": "Leadership 3+", "act": "1a?", "cost": "2F", "rng": "varies", "vs": "cog", "eff": "2F: Leadership vs cog of a sensed foe; success -> up to Leadership-ranks allies, fail -> 1 ally; each gains a bonus Strike vs that foe (doesn't count vs their Strike limit) next turn" },
    { "id": "leader-authority", "name": "Authority", "src": "leader", "kind": "talent", "tier": 1, "spec": "Officer", "pre": "Title commanding 5+ people", "act": "none", "cost": "", "rng": "self", "vs": "", "eff": "passive: your ally-affecting Leader talents double their range & double max allies affected" },
    { "id": "leader-cutthroat-tactics", "name": "Cutthroat Tactics", "src": "leader", "kind": "talent", "tier": 1, "spec": "Politico", "pre": "Deception 1+", "act": "none", "cost": "", "rng": "varies", "vs": "", "eff": "when an ally would roll your command die, they may raise stakes instead; a Complication on it -> you regain 1F" },
    { "id": "leader-tactical-ploy", "name": "Tactical Ploy", "src": "leader", "kind": "talent", "tier": 1, "spec": "Politico", "pre": "", "act": "1a?", "cost": "", "rng": "varies", "vs": "cog", "eff": "Deception vs cog of an influenceable foe; success -> they lose 1F & take disadv on next cog/spir test; if they resist, you gain adv vs them EONT" },
    { "id": "leader-rumormonger", "name": "Rumormonger", "src": "leader", "kind": "talent", "tier": 1, "spec": "Politico", "pre": "A patron", "act": "none", "cost": "2F", "rng": "self", "vs": "", "eff": "gain Scandal expertise; on a test to spread misinformation/gather rumors, 2F -> add an Opportunity" },
    { "id": "leader-well-dressed", "name": "Well Dressed", "src": "leader", "kind": "talent", "tier": 1, "spec": "Politico", "pre": "", "act": "none", "cost": "", "rng": "self", "vs": "", "eff": "gain Fashion expertise; while visibly in Presentable armor/fashionable clothing, adv on your first Deception/Leadership/Persuasion test each scene" },
    { "id": "leader-baleful", "name": "Baleful", "src": "leader", "kind": "talent", "tier": 1, "spec": "Politico", "pre": "", "act": "none", "cost": "", "rng": "self", "vs": "", "eff": "passive: resisting your influence costs a character extra F equal to your tier" },
    { "id": "leader-set-at-odds", "name": "Set at Odds", "src": "leader", "kind": "talent", "tier": 1, "spec": "Politico", "pre": "Leadership 3+", "act": "1a?", "cost": "var", "rng": "varies", "vs": "spir", "eff": "pick 2+ influenceable targets, spend that many F; Leadership vs highest spir among them -> success makes them mutually hostile until resolved; a resister loses extra F = Leadership ranks" },
    { "id": "leader-shrewd-command", "name": "Shrewd Command", "src": "leader", "kind": "talent", "tier": 1, "spec": "Politico", "pre": "Leadership 2+", "act": "free", "cost": "1F", "rng": "self", "vs": "", "eff": "command die +1 size on gain; before a Deception/Insight/Leadership test, 1F -> roll command die & add to your d20" },
    { "id": "leader-grand-deception", "name": "Grand Deception", "src": "leader", "kind": "talent", "tier": 1, "spec": "Politico", "pre": "Deception 3+", "act": "1a?", "cost": "3F", "rng": "self", "vs": "", "eff": "3F: Deception DC15; success -> reveal that a plausible detail established since last scene's start was actually a ruse, changing it (GM adjudicates)" },
    { "id": "scholar-efficient-engineer", "name": "Efficient Engineer", "src": "scholar", "kind": "talent", "tier": 1, "spec": "Artifabrian", "pre": "Crafting 1+", "act": "none", "cost": "", "rng": "self", "vs": "", "eff": "passive: gain a Crafting expertise (armor/equipment/weapon) + a free fabrial; crafting tests get +2 Opportunity range, raw-material cost halved" },
    { "id": "scholar-prized-acquisition", "name": "Prized Acquisition", "src": "scholar", "kind": "talent", "tier": 1, "spec": "Artifabrian", "pre": "", "act": "none", "cost": "", "rng": "self", "vs": "", "eff": "passive: gain Fabrial Crafting expertise + a cut gem; first craft w/ it skips the spren-attract/craft time (still needs materials); gem matches your tier, reusable" },
    { "id": "scholar-deep-study", "name": "Deep Study", "src": "scholar", "kind": "talent", "tier": 1, "spec": "Artifabrian", "pre": "", "act": "none", "cost": "", "rng": "self", "vs": "", "eff": "passive: Erudition also grants +1 cultural/utility expertise and +2 non-surge cognitive skills; reassignable like the rest" },
    { "id": "scholar-inventive-design", "name": "Inventive Design", "src": "scholar", "kind": "talent", "tier": 1, "spec": "Artifabrian", "pre": "Crafting 2+", "act": "none", "cost": "", "rng": "self", "vs": "", "eff": "passive: when crafting a fabrial w/ your Prized Acquisition gem, you may pick an effect 1 tier above the tier being crafted" },
    { "id": "scholar-fine-handiwork", "name": "Fine Handiwork", "src": "scholar", "kind": "talent", "tier": 1, "spec": "Artifabrian", "pre": "", "act": "none", "cost": "", "rng": "self", "vs": "", "eff": "passive: when crafting, an advanced feature costs 1 upgrade instead of 2; once per item" },
    { "id": "scholar-overcharge", "name": "Overcharge", "src": "scholar", "kind": "talent", "tier": 1, "spec": "Artifabrian", "pre": "Crafting 3+", "act": "none", "cost": "", "rng": "self", "vs": "", "eff": "1/turn: on a fabrial atk test, raise stakes; spend -> free Strike w/ that fabrial (not counted vs Strike limit). GM may spend -> add a drawback until you pass DC15 Crafting" },
    { "id": "scholar-experimental-tinkering", "name": "Experimental Tinkering", "src": "scholar", "kind": "talent", "tier": 1, "spec": "Artifabrian", "pre": "", "act": "none", "cost": "", "rng": "self", "vs": "", "eff": "passive: crafting gets +1 Opportunity range, time halved; on a long rest, reconfigure your Prized Acquisition fabrial into another of equal/lower tier (no materials/time; fail Lore -> keep old)" },
    { "id": "scholar-overwhelm-with-detail", "name": "Overwhelm With Detail", "src": "scholar", "kind": "talent", "tier": 1, "spec": "Artifabrian", "pre": "Lore 3+", "act": "free?", "cost": "2F", "rng": "self", "vs": "", "eff": "2F: substitute your Lore modifier for the normal skill modifier on a cognitive or spiritual test" },
    { "id": "scholar-strategize", "name": "Strategize", "src": "scholar", "kind": "talent", "tier": 1, "spec": "Strategist", "pre": "Deduction 1+", "act": "free?", "cost": "", "rng": "varies", "vs": "", "eff": "after you succeed at Gain Advantage w/ an Erudition skill, redirect that advantage to an influenceable ally; 2F -> the target can't use reactions vs that ally EONT" },
    { "id": "scholar-mind-and-body", "name": "Mind and Body", "src": "scholar", "kind": "talent", "tier": 1, "spec": "Strategist", "pre": "", "act": "none", "cost": "", "rng": "self", "vs": "", "eff": "passive: Erudition grants +1 skill and may now pick non-surge physical skills; also gain 1 weapon expertise" },
    { "id": "scholar-composed", "name": "Composed", "src": "scholar", "kind": "talent", "tier": 1, "spec": "Strategist", "pre": "", "act": "none", "cost": "", "rng": "self", "vs": "", "eff": "passive: max + current F rise by your tier; rises again each time tier increases" },
    { "id": "scholar-know-your-moment", "name": "Know Your Moment", "src": "scholar", "kind": "talent", "tier": 1, "spec": "Strategist", "pre": "Deduction 2+", "act": "none", "cost": "", "rng": "self", "vs": "", "eff": "passive: at each round's start, all your defenses +2 until your turn begins" },
    { "id": "scholar-deep-contemplation", "name": "Deep Contemplation", "src": "scholar", "kind": "talent", "tier": 1, "spec": "Strategist", "pre": "Lore 2+", "act": "var", "cost": "", "rng": "self", "vs": "", "eff": "swap as many as two of the skills/expertises Erudition gave you" },
    { "id": "scholar-keen-insight", "name": "Keen Insight", "src": "scholar", "kind": "talent", "tier": 1, "spec": "Strategist", "pre": "", "act": "free?", "cost": "", "rng": "varies", "vs": "spir", "eff": "after a successful Gain Advantage, the target takes disadv on its next test this encounter unless it shrugs off your sway" },
    { "id": "scholar-contingency", "name": "Contingency", "src": "scholar", "kind": "talent", "tier": 1, "spec": "Strategist", "pre": "Lore 3+", "act": "rea", "cost": "2F", "rng": "20ft", "vs": "", "eff": "trigger: influenceable ally within 20ft rolls a Complication -> spend 2F to cancel a Complication on their test" },
    { "id": "scholar-turning-point", "name": "Turning Point", "src": "scholar", "kind": "talent", "tier": 1, "spec": "Strategist", "pre": "Deduction 3+", "act": "1a?", "cost": "2F", "rng": "varies", "vs": "cog", "eff": "1/scene, 2F: Deduction vs cog of the top enemy leader you can sense (adv if you went slow this turn); success -> you + influenceable allies gain an extra plot die on your next turns" },
    { "id": "scholar-field-medicine", "name": "Field Medicine", "src": "scholar", "kind": "talent", "tier": 1, "spec": "Surgeon", "pre": "Medicine 1+", "act": "1a?", "cost": "1F", "rng": "reach", "vs": "", "eff": "1F: DC15 Medicine to treat a willing conscious target in reach, roll their recovery die (disadv if self); success -> heal recovery die + Medicine ranks; fail -> recovery die only" },
    { "id": "scholar-emotional-intelligence", "name": "Emotional Intelligence", "src": "scholar", "kind": "talent", "tier": 1, "spec": "Surgeon", "pre": "", "act": "none", "cost": "", "rng": "self", "vs": "", "eff": "passive: Erudition grants +1 skill and may now pick non-surge spiritual skills; also gain Diagnosis utility expertise" },
    { "id": "scholar-anatomical-insight", "name": "Anatomical Insight", "src": "scholar", "kind": "talent", "tier": 1, "spec": "Surgeon", "pre": "", "act": "free?", "cost": "1F", "rng": "melee", "vs": "", "eff": "on hitting a target your size or smaller w/ an unarmed atk, spend 1F or a plot die -> apply Exhausted, penalty = half your Medicine ranks (round up)" },
    { "id": "scholar-collected", "name": "Collected", "src": "scholar", "kind": "talent", "tier": 1, "spec": "Surgeon", "pre": "", "act": "none", "cost": "", "rng": "self", "vs": "", "eff": "passive: Cognitive and Spiritual defenses +2" },
    { "id": "scholar-swift-healer", "name": "Swift Healer", "src": "scholar", "kind": "talent", "tier": 1, "spec": "Surgeon", "pre": "Medicine 2+", "act": "none", "cost": "", "rng": "self", "vs": "", "eff": "passive: Field Medicine usable as a faster action; any health you restore to others gains +your Medicine ranks" },
    { "id": "scholar-applied-medicine", "name": "Applied Medicine", "src": "scholar", "kind": "talent", "tier": 1, "spec": "Surgeon", "pre": "Lore 2+", "act": "none", "cost": "", "rng": "self", "vs": "", "eff": "passive: whenever you make a character recover health, they recover +your Lore ranks extra" },
    { "id": "scholar-ongoing-care", "name": "Ongoing Care", "src": "scholar", "kind": "talent", "tier": 1, "spec": "Surgeon", "pre": "Lore 3+", "act": "var", "cost": "", "rng": "reach", "vs": "", "eff": "spend a short/long rest treating an ally in reach -> DC10 Medicine (+5 per injury past the first); success removes 1 injury-caused condition (injury stays). 1/24h per target. Gain Mental Health Care expertise" },
    { "id": "scholar-resuscitation", "name": "Resuscitation", "src": "scholar", "kind": "talent", "tier": 1, "spec": "Surgeon", "pre": "Medicine 3+", "act": "1a?", "cost": "3F", "rng": "reach", "vs": "", "eff": "use Field Medicine w/ 3F (not 1F) on a target in reach who is Unconscious or died within (Medicine ranks) rounds; DC +5 per extra injury; success heals + revives the dead, Unconscious may drop that condition" },
    { "id": "warrior-feinting-strike", "name": "Feinting Strike", "src": "warrior", "kind": "talent", "tier": 1, "spec": "Duelist", "pre": "Intimidation 2+", "act": "1a?", "cost": "2F", "rng": "melee", "vs": "cog", "eff": "melee weapon atk vs cog; hit -> foe loses 1 action + F equal to your Intimidation ranks; graze -> half F, no action loss; Opportunity -> action usable only to Strike/enter a stance" },
    { "id": "warrior-flamestance", "name": "Flamestance", "src": "warrior", "kind": "talent", "tier": 1, "spec": "Duelist", "pre": "Intimidation 1+", "act": "1a?", "cost": "", "rng": "self", "vs": "", "eff": "stance: adv on Intimidation; if exactly 1 enemy in reach + no allies near it/you, free action -> gain action usable only to Gain Advantage or atk vs that enemy" },
    { "id": "warrior-ironstance", "name": "Ironstance", "src": "warrior", "kind": "talent", "tier": 1, "spec": "Duelist", "pre": "Athletics 2+", "act": "1a?", "cost": "", "rng": "self", "vs": "", "eff": "stance: adv on Insight; when a foe in reach misses or grazes you, Reactive Strike them as if they'd left your reach" },
    { "id": "warrior-practiced-kata", "name": "Practiced Kata", "src": "warrior", "kind": "talent", "tier": 1, "spec": "Duelist", "pre": "", "act": "none", "cost": "", "rng": "self", "vs": "", "eff": "use stances in conversation/endeavor scenes too (entering/changing costs 1F + counts as a round contribution); if not Surprised at scene start, enter Vigilant Stance free" },
    { "id": "warrior-signature-weapon", "name": "Signature Weapon", "src": "warrior", "kind": "talent", "tier": 1, "spec": "Duelist", "pre": "", "act": "none", "cost": "", "rng": "self", "vs": "", "eff": "gain 1 weapon expertise; pick a weapon type you're expert in -> its Opportunity range +1 (+2 at tier 3)" },
    { "id": "warrior-surefooted", "name": "Surefooted", "src": "warrior", "kind": "talent", "tier": 1, "spec": "Duelist", "pre": "", "act": "none", "cost": "", "rng": "self", "vs": "", "eff": "passive: movement +10; reduce falling/dangerous-terrain damage by 2x tier" },
    { "id": "warrior-vinestance", "name": "Vinestance", "src": "warrior", "kind": "talent", "tier": 1, "spec": "Duelist", "pre": "Athletics 3+", "act": "1a?", "cost": "", "rng": "self", "vs": "cog", "eff": "stance: phys & cog defense +1; after hit/grazed in melee, reaction -> Athletics vs cog; success -> attacker loses 1d4 F + pushed up to 5ft x Athletics ranks" },
    { "id": "warrior-wits-end", "name": "Wit's End", "src": "warrior", "kind": "talent", "tier": 1, "spec": "Duelist", "pre": "Intimidation 3+", "act": "1a?", "cost": "1F", "rng": "melee", "vs": "cog", "eff": "move half movement, then melee weapon atk vs cog of a target with 0 F; ignores deflect, +4d6 dmg (6d6 t3, 8d6 t4, 10d6 t5), can't graze" },
    { "id": "warrior-bloodstance", "name": "Bloodstance", "src": "warrior", "kind": "talent", "tier": 1, "spec": "Shardbearer", "pre": "Athletics 2+", "act": "1a?", "cost": "", "rng": "self", "vs": "", "eff": "stance: Opportunity range for atk & physical tests +2, but phys/cog/spir defenses -2" },
    { "id": "warrior-meteoric-leap", "name": "Meteoric Leap", "src": "warrior", "kind": "talent", "tier": 1, "spec": "Shardbearer", "pre": "Athletics 3+", "act": "1a?", "cost": "2F", "rng": "reach", "vs": "phys", "eff": "leap up to 1/4 movement, then unarmed atk vs phys of each chosen target in reach; double dmg dice; hit -> targets with lower Strength knocked Prone; adv in Shardplate" },
    { "id": "warrior-mighty", "name": "Mighty", "src": "warrior", "kind": "talent", "tier": 1, "spec": "Shardbearer", "pre": "", "act": "none", "cost": "", "rng": "self", "vs": "", "eff": "passive: on a weapon/unarmed hit, per action spent on that atk deal +1+tier dmg" },
    { "id": "warrior-precise-parry", "name": "Precise Parry", "src": "warrior", "kind": "talent", "tier": 1, "spec": "Shardbearer", "pre": "Perception 3+", "act": "rea", "cost": "1F", "rng": "self", "vs": "", "eff": "before a melee hit lands, parry: unarmed -> Athletics (disadv unless vs Shardblade), Opportunity disarms; armed -> Weaponry test, a Shardblade can destroy a non-Invested weapon via Opportunity; DC = atk result, success -> hit becomes a graze" },
    { "id": "warrior-shard-training", "name": "Shard Training", "src": "warrior", "kind": "talent", "tier": 1, "spec": "Shardbearer", "pre": "Access to Shardblade & Shardplate", "act": "none", "cost": "", "rng": "self", "vs": "phys", "eff": "1/round a Shardblade Strike also grazes extra enemies (up to skill ranks used) in reach whose phys defense <= test result, free; gain Shardplate + Grandbow/Shardblade/Warhammer expertise; your Shardplate +2 charges" },
    { "id": "warrior-shattering-blow", "name": "Shattering Blow", "src": "warrior", "kind": "talent", "tier": 1, "spec": "Shardbearer", "pre": "Perception 2+", "act": "free?", "cost": "2F", "rng": "melee", "vs": "", "eff": "on a melee hit while wielding two-handed or with a hand free, 2F -> target's charged armor loses 1 charge; each target that lost health pushed 5ft (+5ft per Strength above 5), impact damage vs a large object" },
    { "id": "warrior-stonestance", "name": "Stonestance", "src": "warrior", "kind": "talent", "tier": 1, "spec": "Shardbearer", "pre": "", "act": "1a?", "cost": "", "rng": "self", "vs": "", "eff": "stance: deflect +1; a foe in reach must spend 1 extra action to hit allies of yours not also in Stonestance" },
    { "id": "warrior-windstance", "name": "Windstance", "src": "warrior", "kind": "talent", "tier": 1, "spec": "Shardbearer", "pre": "Perception 1+", "act": "1a?", "cost": "", "rng": "self", "vs": "", "eff": "stance: adv on Agility; while 2+ enemies in reach, free action -> gain action usable only to Disengage or atk those enemies" },
    { "id": "warrior-cautious-advance", "name": "Cautious Advance", "src": "warrior", "kind": "talent", "tier": 1, "spec": "Soldier", "pre": "Discipline 1+", "act": "1a?", "cost": "", "rng": "self", "vs": "", "eff": "move up to half speed (ignore difficult terrain), then gain an action only for Brace or Gain Advantage" },
    { "id": "warrior-combat-training", "name": "Combat Training", "src": "warrior", "kind": "talent", "tier": 1, "spec": "Soldier", "pre": "", "act": "none", "cost": "", "rng": "self", "vs": "", "eff": "1/round on a missed weapon atk, graze 1 target free; gain weapon + armor + Military Life cultural expertise" },
    { "id": "warrior-defensive-position", "name": "Defensive Position", "src": "warrior", "kind": "talent", "tier": 1, "spec": "Soldier", "pre": "Athletics 2+", "act": "none", "cost": "", "rng": "self", "vs": "", "eff": "your Brace adds 2 disadv to atks vs you (not 1); while you Brace with a shield, allies within 5ft gain that cover/shield Brace too" },
    { "id": "warrior-devastating-blow", "name": "Devastating Blow", "src": "warrior", "kind": "talent", "tier": 1, "spec": "Soldier", "pre": "Athletics 3+", "act": "1a?", "cost": "", "rng": "melee", "vs": "phys", "eff": "melee weapon atk vs phys, +2d8 dmg (3d8 t3, 4d8 t4, 5d8 t5)" },
    { "id": "warrior-formation-drills", "name": "Formation Drills", "src": "warrior", "kind": "talent", "tier": 1, "spec": "Soldier", "pre": "Discipline 2+", "act": "none", "cost": "", "rng": "10ft", "vs": "", "eff": "an ally within 10ft who is Bracing also gets your Defensive Position effect" },
    { "id": "warrior-hardy", "name": "Hardy", "src": "warrior", "kind": "talent", "tier": 1, "spec": "Soldier", "pre": "", "act": "none", "cost": "", "rng": "self", "vs": "", "eff": "passive: max & current health +1 per level, applied retroactively to all levels" },
    { "id": "warrior-swift-strikes", "name": "Swift Strikes", "src": "warrior", "kind": "talent", "tier": 1, "spec": "Soldier", "pre": "", "act": "free?", "cost": "1F", "rng": "self", "vs": "", "eff": "1F -> Strike again using a hand that already Struck this turn" },
    { "id": "warrior-wary", "name": "Wary", "src": "warrior", "kind": "talent", "tier": 1, "spec": "Soldier", "pre": "Discipline 3+", "act": "none", "cost": "", "rng": "self", "vs": "", "eff": "immune to Surprised whenever you hold 1+ F; when resisting influence or losing F involuntarily, cut the F lost by Discipline ranks (min 1)" }
  ]
}
